{
    "light": "#ffffff",
    "dark": "#2D2D2D",
    "neutral": "#FFFEF5",
    "neutralAlt": "#FFF9E6",
    "primary": "#F5D547",
    "fontBody": "epilogue",
    "fontHeadlines": "epilogue",
    "h1": {
        "size": "6xl",
        "weight": "semibold",
        "decoration": "none",
        "case": "none",
        "letterSpacing": "normal",
        "type": "ThemeStyleHeading"
    },
    "h2": {
        "size": "5xl",
        "weight": "semibold",
        "decoration": "none",
        "case": "none",
        "letterSpacing": "normal",
        "type": "ThemeStyleHeading"
    },
    "h3": {
        "size": "3xl",
        "weight": "semibold",
        "decoration": "none",
        "case": "none",
        "letterSpacing": "normal",
        "type": "ThemeStyleHeading"
    },
    "h4": {
        "size": "2xl",
        "weight": "semibold",
        "decoration": "none",
        "case": "none",
        "letterSpacing": "normal",
        "type": "ThemeStyleHeading"
    },
    "h5": {
        "size": "xl",
        "weight": "semibold",
        "decoration": "none",
        "case": "none",
        "letterSpacing": "normal",
        "type": "ThemeStyleHeading"
    },
    "h6": {
        "size": "lg",
        "weight": "semibold",
        "decoration": "none",
        "case": "none",
        "letterSpacing": "normal",
        "type": "ThemeStyleHeading"
    },
    "buttonPrimary": {
        "weight": "semibold",
        "case": "none",
        "letterSpacing": "normal",
        "borderRadius": "none",
        "shadow": "none",
        "horizontalPadding": 82,
        "verticalPadding": 25,
        "type": "ThemeStyleButton"
    },
    "buttonSecondary": {
        "weight": "normal",
        "case": "none",
        "letterSpacing": "normal",
        "borderRadius": "none",
        "shadow": "none",
        "horizontalPadding": 30,
        "verticalPadding": 12,
        "type": "ThemeStyleButton"
    },
    "linkPrimary": {
        "weight": "normal",
        "case": "none",
        "letterSpacing": "normal",
        "type": "ThemeStyleLink"
    },
    "linkSecondary": {
        "weight": "normal",
        "case": "none",
        "letterSpacing": "normal",
        "type": "ThemeStyleLink"
    },
    "type": "ThemeStyle"
}
